README.md
setup.py
analog_image_caption/__init__.py
analogcaption.egg-info/PKG-INFO
analogcaption.egg-info/SOURCES.txt
analogcaption.egg-info/dependency_links.txt
analogcaption.egg-info/requires.txt
analogcaption.egg-info/top_level.txt