Metadata-Version: 2.1
Name: analogcaption
Version: 0.1.0
Summary: A Package that uses AI to give users the caption of an image
Home-page: https://bitbucket.org/Lormenyoh/image-caption-generator/src/master/
Author: Analog Teams
Author-email: james@analogteams.com
License: The MIT License
Platform: UNKNOWN
